CHANGES.rst
LICENSE.txt
MANIFEST.in
README.rst
setup.py
src/timeout_wrapper/__init__.py
src/timeout_wrapper/timeout.py
src/timeout_wrapper.egg-info/PKG-INFO
src/timeout_wrapper.egg-info/SOURCES.txt
src/timeout_wrapper.egg-info/dependency_links.txt
src/timeout_wrapper.egg-info/requires.txt
src/timeout_wrapper.egg-info/top_level.txt
src/timeout_wrapper.egg-info/zip-safe
tests/test_timeout.py