Metadata-Version: 1.1
Name: timeout-wrapper
Version: 0.1.0
Summary: Timeout decorator with defaults and exceptions.
Home-page: https://github.com/Bystroushaak/timeout_wrapper
Author: Bystroushaak
Author-email: bystrousak@kitakitsune.org
License: MIT
Platform: UNKNOWN
Classifier: Intended Audience :: Developers
Classifier: Programming Language :: Python :: 2
Classifier: Programming Language :: Python :: 2.7
Classifier: License :: OSI Approved :: MIT License
